[
    {"text": "Paris is the capital of France.", "triples": "Paris|is capital of|France"},
    {"text": "Albert Einstein developed the theory of relativity.", "triples": "Albert Einstein|developed|theory of relativity"},
    {"text": "The Moon revolves around the Earth.", "triples": "Moon|revolves around|Earth"},
    {"text": "Water boils at 100 degrees Celsius.", "triples": "Water|boils at|100 degrees Celsius"},
    {"text": "The Taj Mahal is located in India.", "triples": "Taj Mahal|is located in|India"},
    {"text": "The Nile flows through Egypt.", "triples": "Nile|flows through|Egypt"},
    {"text": "Mount Everest is the highest mountain on Earth.", "triples": "Mount Everest|is highest mountain on|Earth"},
    {"text": "Bananas are rich in potassium.", "triples": "Bananas|are rich in|potassium"},
    {"text": "The Pacific Ocean is the largest ocean on Earth.", "triples": "Pacific Ocean|is largest ocean on|Earth"},
    {"text": "The Eiffel Tower was built in 1889.", "triples": "Eiffel Tower|was built in|1889"},
    {"text": "Lightning is caused by the discharge of electricity in the atmosphere.", "triples": "Lightning|is caused by|discharge of electricity in atmosphere"},
    {"text": "Elephants are the largest land animals.", "triples": "Elephants|are|largest land animals"},
    {"text": "The Great Wall of China is visible from space.", "triples": "Great Wall of China|is visible from|space"},
    {"text": "The Statue of Liberty is a symbol of freedom.", "triples": "Statue of Liberty|is symbol of|freedom"},
    {"text": "The sun rises in the east.", "triples": "Sun|rises in|east"},
    {"text": "The Amazon River is the longest river in South America.", "triples": "Amazon River|is longest river in|South America"},
    {"text": "Tom Hanks starred in the movie Forrest Gump.", "triples": "Tom Hanks|starred in|Forrest Gump"},
    {"text": "The cat is sitting on the mat.", "triples": "Cat|is sitting on|mat"},
    {"text": "Isaac Newton formulated the laws of motion.", "triples": "Isaac Newton|formulated|laws of motion"},
    {"text": "The Statue of Liberty was gifted by France.", "triples": "France|gifted|Statue of Liberty"},
    {"text": "The Great Pyramid of Giza is in Egypt.", "triples": "Great Pyramid of Giza|is in|Egypt"},
    {"text": "Shakespeare wrote Hamlet.", "triples": "Shakespeare|wrote|Hamlet"},
    {"text": "Honey is produced by bees.", "triples": "Bees|produce|honey"},
    {"text": "Mount Kilimanjaro is the highest mountain in Africa.", "triples": "Mount Kilimanjaro|is highest mountain in|Africa"},
    {"text": "Coffee is grown in Colombia.", "triples": "Coffee|is grown in|Colombia"},
    {"text": "The Pacific Ocean borders the west coast of the USA.", "triples": "Pacific Ocean|borders west coast of|USA"},
    {"text": "Google was founded by Larry Page and Sergey Brin.", "triples": "Larry Page and Sergey Brin|founded|Google"},
    {"text": "The currency of Japan is the Yen.", "triples": "Currency of Japan|is|Yen"},
    {"text": "The Statue of Liberty stands on Liberty Island.", "triples": "Statue of Liberty|stands on|Liberty Island"},
    {"text": "The temperature in Sahara can reach over 50 degrees Celsius.", "triples": "Temperature in Sahara|can reach|over 50 degrees Celsius"},
    {"text": "Cheetahs are the fastest land animals.", "triples": "Cheetahs|are|fastest land animals"},
    {"text": "The Golden Gate Bridge is located in San Francisco.", "triples": "Golden Gate Bridge|is located in|San Francisco"},
    {"text": "The Amazon rainforest is the largest tropical rainforest.", "triples": "Amazon rainforest|is largest tropical rainforest|"},
    {"text": "The battery life of this phone is 24 hours.", "triples": "Battery life of phone|is|24 hours"},
    {"text": "Barack Obama was the 44th president of the United States.", "triples": "Barack Obama|was|44th president of United States"},
    {"text": "The Great Barrier Reef is off the coast of Australia.", "triples": "Great Barrier Reef|is off the coast of|Australia"},
    {"text": "J.K. Rowling wrote the Harry Potter series.", "triples": "J.K. Rowling|wrote|Harry Potter series"},
    {"text": "Silver is a precious metal.", "triples": "Silver|is|precious metal"},
    {"text": "The Berlin Wall fell in 1989.", "triples": "Berlin Wall|fell in|1989"},
    {"text": "Venus is the second planet from the Sun.", "triples": "Venus|is second planet from|Sun"},
    {"text": "Google headquarters is in Mountain View.", "triples": "Google headquarters|is in|Mountain View"},
    {"text": "The speed of sound is approximately 343 meters per second.", "triples": "Speed of sound|is approximately|343 meters per second"},
    {"text": "The population of New York City is about 8.4 million.", "triples": "Population of New York City|is about|8.4 million"},
    {"text": "The Sahara Desert is the largest hot desert.", "triples": "Sahara Desert|is largest hot desert|"},
    {"text": "Honey never spoils.", "triples": "Honey|never spoils|"},
    {"text": "Python is a popular programming language.", "triples": "Python|is|popular programming language"},
    {"text": "The Great Lakes consist of five lakes.", "triples": "Great Lakes|consist of|five lakes"},
    {"text": "Mount Fuji is located in Japan.", "triples": "Mount Fuji|is located in|Japan"},
    {"text": "The currency of the United Kingdom is the Pound Sterling.", "triples": "Currency of United Kingdom|is|Pound Sterling"}
]
